yolov8mini/__init__.py
yolov8mini/bot.py
yolov8mini-2.3.1.dist-info/METADATA
yolov8mini-2.3.1.dist-info/WHEEL
yolov8mini-2.3.1.dist-info/entry_points.txt
yolov8mini-2.3.1.dist-info/top_level.txt
yolov8mini-2.3.1.dist-info/RECORD
